<?xml version="1.0" encoding="utf-8" ?>
<dwsync>
<file name="alert.gif" server="184.168.42.1//" local="129564928800000000" remote="129564928800000000" />
<file name="button.gif" server="184.168.42.1//" local="129564928800000000" remote="129564928800000000" />
<file name="buttons.gif" server="184.168.42.1//" local="129564928800000000" remote="129564928800000000" />
<file name="confirm.gif" server="184.168.42.1//" local="129564928800000000" remote="129564928800000000" />
<file name="corners.gif" server="184.168.42.1//" local="129564928800000000" remote="129564928800000000" />
<file name="drag.gif" server="184.168.42.1//" local="129564928800000000" remote="129564928800000000" />
<file name="horizontal.gif" server="184.168.42.1//" local="129564928800000000" remote="129564928800000000" />
<file name="vertical.gif" server="184.168.42.1//" local="129564928800000000" remote="129564928800000000" />
<file name="buttons.gif" server="184.168.42.1" local="129564928800000000" remote="129586437000000000" />
<file name="alert.gif" server="184.168.42.1" local="129564928800000000" remote="129586437000000000" />
<file name="button.gif" server="184.168.42.1" local="129564928800000000" remote="129586437000000000" />
<file name="confirm.gif" server="184.168.42.1" local="129564928800000000" remote="129586437000000000" />
<file name="corners.gif" server="184.168.42.1" local="129564928800000000" remote="129586437000000000" />
<file name="drag.gif" server="184.168.42.1" local="129564928800000000" remote="129586437600000000" />
<file name="horizontal.gif" server="184.168.42.1" local="129564928800000000" remote="129586437600000000" />
<file name="vertical.gif" server="184.168.42.1" local="129564928800000000" remote="129586437600000000" />
</dwsync>